[
  {
    "id": "P000219708",
    "name": "Dockers® Metal Pilot Polarized Sunglasses",
    "long_description": "These Dockers sunglasses combine the classic pilot look with a metal frame & polarized lenses and offer 100% UV protection. International Shipping Prohibited.",
    "brand": "Dockers®",
    "slug": "/dockers%C2%AE-metal-pilot-polarized-sunglasses-p000219708/p",
    "product_ref": "P000219708",
    "product_type": null,
    "seo_title": "Dockers® Metal Pilot Polarized Sunglasses",
    "seo_description": "These Dockers sunglasses combine the classic pilot look with a metal frame & polarized lenses and offer 100% UV protection. International Shipping Prohibited.",
    "seo_keywords": "Dockers® Metal Pilot Polarized Sunglasses, Dockers®",
    "display_on_site": true,
    "tax_code": "txcd_99999999",
    "related_products": [],
    "reviews": {
      "bayesian_avg": 3.31,
      "count": 69,
      "rating": 3
    },
    "hierarchical_categories": {
      "lvl0": "Men",
      "lvl1": "Men > Accessories",
      "lvl2": "Men > Accessories > Mens Sunglasses"
    },
    "list_categories": [
      "Men",
      "Accessories",
      "Mens Sunglasses"
    ],
    "created_at": null,
    "updated_at": null,
    "created_by": null,
    "updated_by": null,
    "defining_attributes": {
      "color": "Color",
      "size": "Size"
    },
    "descriptive_attributes": {
      "Material": "Cotton",
      "Country of Origin": "United States",
      "Care Instructions": "Machine Wash"
    },
    "default_variant": "0093097367",
    "variants": [
      {
        "defining_attributes": {
          "color": "GUNMETAL GREY",
          "size": "No Sz"
        },
        "abbreviated_color": "",
        "sku": "0093097367",
        "height": 0,
        "width": 0,
        "length": 0,
        "weight": 0,
        "weight_unit": "lb",
        "packaging": {
          "height": 0,
          "width": 0,
          "length": 0,
          "weight": 0,
          "weight_unit": "lb"
        },
        "image_urls": [
          "https://res.cloudinary.com/dau8m6xke/image/upload/products/Dockers-Metal-Pilot-Polarized-Sunglasses-GUNMETAL-GREY-0093097367.jpg"
        ]
      }
    ]
  },
  {
    "id": "P000220054",
    "name": "A. Byer Shutter Crochet Back Tank Top",
    "long_description": "This tank top by A. Byer features figure-flattering asymmetrical tiers on the front, solid design and a racerback with lace details.",
    "brand": "A. Byer",
    "slug": "/a--byer-shutter-crochet-back-tank-top-p000220054/p",
    "product_ref": "P000220054",
    "product_type": null,
    "seo_title": "A. Byer Shutter Crochet Back Tank Top",
    "seo_description": "This tank top by A. Byer features figure-flattering asymmetrical tiers on the front, solid design and a racerback with lace details.",
    "seo_keywords": "A. Byer Shutter Crochet Back Tank Top, A. Byer",
    "display_on_site": true,
    "tax_code": "txcd_99999999",
    "related_products": [],
    "reviews": {
      "bayesian_avg": 3.72,
      "count": 195,
      "rating": 4
    },
    "hierarchical_categories": {
      "lvl0": "Women",
      "lvl1": "Women > Juniors Apparel",
      "lvl2": "Women > Juniors Apparel > Tank Tops"
    },
    "list_categories": [
      "Women",
      "Juniors Apparel",
      "Tank Tops"
    ],
    "created_at": null,
    "updated_at": null,
    "created_by": null,
    "updated_by": null,
    "defining_attributes": {
      "color": "Color",
      "size": "Size"
    },
    "descriptive_attributes": {
      "Material": "Cotton",
      "Country of Origin": "United States",
      "Care Instructions": "Machine Wash"
    },
    "default_variant": "0095996190",
    "variants": [
      {
        "defining_attributes": {
          "color": "YELLOW",
          "size": "Md"
        },
        "abbreviated_color": "",
        "sku": "0095996190",
        "height": 0,
        "width": 0,
        "length": 0,
        "weight": 0,
        "weight_unit": "lb",
        "packaging": {
          "height": 0,
          "width": 0,
          "length": 0,
          "weight": 0,
          "weight_unit": "lb"
        },
        "image_urls": [
          "https://res.cloudinary.com/dau8m6xke/image/upload/products/A-Byer-Shutter-Crochet-Back-Tank-Top-YELLOW-0095996190.jpg"
        ]
      },
      {
        "defining_attributes": {
          "color": "YELLOW",
          "size": "Lg"
        },
        "abbreviated_color": "",
        "sku": "0095996206",
        "height": 0,
        "width": 0,
        "length": 0,
        "weight": 0,
        "weight_unit": "lb",
        "packaging": {
          "height": 0,
          "width": 0,
          "length": 0,
          "weight": 0,
          "weight_unit": "lb"
        },
        "image_urls": [
          "https://res.cloudinary.com/dau8m6xke/image/upload/products/A-Byer-Shutter-Crochet-Back-Tank-Top-YELLOW-0095996206.jpg"
        ]
      },
      {
        "defining_attributes": {
          "size": "Sm",
          "color": "WHITE"
        },
        "abbreviated_color": "",
        "sku": "0095996303",
        "height": 0,
        "width": 0,
        "length": 0,
        "weight": 0,
        "weight_unit": "lb",
        "packaging": {
          "height": 0,
          "width": 0,
          "length": 0,
          "weight": 0,
          "weight_unit": "lb"
        },
        "image_urls": [
          "https://res.cloudinary.com/dau8m6xke/image/upload/products/A-Byer-Shutter-Crochet-Back-Tank-Top-WHITE-0095996303.jpg"
        ]
      },
      {
        "defining_attributes": {
          "size": "Md",
          "color": "WHITE"
        },
        "abbreviated_color": "",
        "sku": "0095996316",
        "height": 0,
        "width": 0,
        "length": 0,
        "weight": 0,
        "weight_unit": "lb",
        "packaging": {
          "height": 0,
          "width": 0,
          "length": 0,
          "weight": 0,
          "weight_unit": "lb"
        },
        "image_urls": [
          "https://res.cloudinary.com/dau8m6xke/image/upload/products/A-Byer-Shutter-Crochet-Back-Tank-Top-WHITE-0095996316.jpg"
        ]
      },
      {
        "defining_attributes": {
          "color": "WHITE",
          "size": "Lg"
        },
        "abbreviated_color": "",
        "sku": "0095996328",
        "height": 0,
        "width": 0,
        "length": 0,
        "weight": 0,
        "weight_unit": "lb",
        "packaging": {
          "height": 0,
          "width": 0,
          "length": 0,
          "weight": 0,
          "weight_unit": "lb"
        },
        "image_urls": [
          "https://res.cloudinary.com/dau8m6xke/image/upload/products/A-Byer-Shutter-Crochet-Back-Tank-Top-WHITE-0095996328.jpg"
        ]
      }
    ]
  },
  {
    "id": "P000207143",
    "name": "Dockers® Large Metal Aviator Sunglasses",
    "long_description": "Protect your eyes from the sun's harsh rays with these Dockers aviator-style sunglasses. 100% UV protection.  International Shipping Prohibited.",
    "brand": "Dockers®",
    "slug": "/dockers%C2%AE-large-metal-aviator-sunglasses-p000207143/p",
    "product_ref": "P000207143",
    "product_type": null,
    "seo_title": "Dockers® Large Metal Aviator Sunglasses",
    "seo_description": "Protect your eyes from the sun's harsh rays with these Dockers aviator-style sunglasses. 100% UV protection.  International Shipping Prohibited.",
    "seo_keywords": "Dockers® Large Metal Aviator Sunglasses, Dockers®",
    "display_on_site": true,
    "tax_code": "txcd_99999999",
    "related_products": [],
    "reviews": {
      "bayesian_avg": 1.32,
      "count": 177,
      "rating": 1
    },
    "hierarchical_categories": {
      "lvl0": "Men",
      "lvl1": "Men > Accessories",
      "lvl2": "Men > Accessories > Mens Sunglasses"
    },
    "list_categories": [
      "Men",
      "Accessories",
      "Mens Sunglasses"
    ],
    "created_at": null,
    "updated_at": null,
    "created_by": null,
    "updated_by": null,
    "defining_attributes": {
      "size": "Size",
      "color": "Color"
    },
    "descriptive_attributes": {
      "Material": "Cotton",
      "Care Instructions": "Machine Wash",
      "Country of Origin": "United States"
    },
    "default_variant": "0093096789",
    "variants": [
      {
        "defining_attributes": {
          "color": "SILVERTONE",
          "size": "No Sz"
        },
        "abbreviated_color": "",
        "sku": "0093096789",
        "height": 0,
        "width": 0,
        "length": 0,
        "weight": 0,
        "weight_unit": "lb",
        "packaging": {
          "height": 0,
          "width": 0,
          "length": 0,
          "weight": 0,
          "weight_unit": "lb"
        },
        "image_urls": [
          "https://res.cloudinary.com/dau8m6xke/image/upload/products/Dockers-Large-Metal-Aviator-Sunglasses-SILVERTONE-0093096789.jpg"
        ]
      }
    ]
  },
  {
    "id": "P000208645",
    "name": "Guy Harvey Deep Marlin Racerback Tank Top",
    "long_description": "Enjoy the comfort and trendy style of this Guy Harvey racerback tank top featuring a lightweight slub knit, marlin print, and mini chest pocket.",
    "brand": "Guy Harvey",
    "slug": "/guy-harvey-deep-marlin-racerback-tank-top-p000208645/p",
    "product_ref": "P000208645",
    "product_type": null,
    "seo_title": "Guy Harvey Deep Marlin Racerback Tank Top",
    "seo_description": "Enjoy the comfort and trendy style of this Guy Harvey racerback tank top featuring a lightweight slub knit, marlin print, and mini chest pocket.",
    "seo_keywords": "Guy Harvey Deep Marlin Racerback Tank Top, Guy Harvey",
    "display_on_site": true,
    "tax_code": "txcd_99999999",
    "related_products": [],
    "reviews": {
      "bayesian_avg": 3.52,
      "count": 185,
      "rating": 4
    },
    "hierarchical_categories": {
      "lvl0": "Women",
      "lvl1": "Women > Juniors Apparel",
      "lvl2": "Women > Juniors Apparel > Tank Tops"
    },
    "list_categories": [
      "Women",
      "Juniors Apparel",
      "Tank Tops"
    ],
    "created_at": null,
    "updated_at": null,
    "created_by": null,
    "updated_by": null,
    "defining_attributes": {
      "size": "Size",
      "color": "Color"
    },
    "descriptive_attributes": {
      "Material": "Cotton",
      "Care Instructions": "Machine Wash",
      "Country of Origin": "United States"
    },
    "default_variant": "0095067752",
    "variants": [
      {
        "defining_attributes": {
          "size": "Sm",
          "color": "TURQUOISE"
        },
        "abbreviated_color": "",
        "sku": "0095067752",
        "height": 0,
        "width": 0,
        "length": 0,
        "weight": 0,
        "weight_unit": "lb",
        "packaging": {
          "height": 0,
          "width": 0,
          "length": 0,
          "weight": 0,
          "weight_unit": "lb"
        },
        "image_urls": [
          "https://res.cloudinary.com/dau8m6xke/image/upload/products/Guy-Harvey-Deep-Marlin-Racerback-Tank-Top-TURQUOISE-0095067752.jpg"
        ]
      },
      {
        "defining_attributes": {
          "size": "Md",
          "color": "TURQUOISE"
        },
        "abbreviated_color": "",
        "sku": "0095067764",
        "height": 0,
        "width": 0,
        "length": 0,
        "weight": 0,
        "weight_unit": "lb",
        "packaging": {
          "height": 0,
          "width": 0,
          "length": 0,
          "weight": 0,
          "weight_unit": "lb"
        },
        "image_urls": [
          "https://res.cloudinary.com/dau8m6xke/image/upload/products/Guy-Harvey-Deep-Marlin-Racerback-Tank-Top-TURQUOISE-0095067764.jpg"
        ]
      },
      {
        "defining_attributes": {
          "color": "TURQUOISE",
          "size": "Lg"
        },
        "abbreviated_color": "",
        "sku": "0095067777",
        "height": 0,
        "width": 0,
        "length": 0,
        "weight": 0,
        "weight_unit": "lb",
        "packaging": {
          "height": 0,
          "width": 0,
          "length": 0,
          "weight": 0,
          "weight_unit": "lb"
        },
        "image_urls": [
          "https://res.cloudinary.com/dau8m6xke/image/upload/products/Guy-Harvey-Deep-Marlin-Racerback-Tank-Top-TURQUOISE-0095067777.jpg"
        ]
      },
      {
        "defining_attributes": {
          "color": "WHITE",
          "size": "Sm"
        },
        "abbreviated_color": "",
        "sku": "0095067789",
        "height": 0,
        "width": 0,
        "length": 0,
        "weight": 0,
        "weight_unit": "lb",
        "packaging": {
          "height": 0,
          "width": 0,
          "length": 0,
          "weight": 0,
          "weight_unit": "lb"
        },
        "image_urls": [
          "https://res.cloudinary.com/dau8m6xke/image/upload/products/Guy-Harvey-Deep-Marlin-Racerback-Tank-Top-WHITE-0095067789.jpg"
        ]
      },
      {
        "defining_attributes": {
          "color": "WHITE",
          "size": "Md"
        },
        "abbreviated_color": "",
        "sku": "0095067791",
        "height": 0,
        "width": 0,
        "length": 0,
        "weight": 0,
        "weight_unit": "lb",
        "packaging": {
          "height": 0,
          "width": 0,
          "length": 0,
          "weight": 0,
          "weight_unit": "lb"
        },
        "image_urls": [
          "https://res.cloudinary.com/dau8m6xke/image/upload/products/Guy-Harvey-Deep-Marlin-Racerback-Tank-Top-WHITE-0095067791.jpg"
        ]
      },
      {
        "defining_attributes": {
          "size": "Lg",
          "color": "WHITE"
        },
        "abbreviated_color": "",
        "sku": "0095067807",
        "height": 0,
        "width": 0,
        "length": 0,
        "weight": 0,
        "weight_unit": "lb",
        "packaging": {
          "height": 0,
          "width": 0,
          "length": 0,
          "weight": 0,
          "weight_unit": "lb"
        },
        "image_urls": [
          "https://res.cloudinary.com/dau8m6xke/image/upload/products/Guy-Harvey-Deep-Marlin-Racerback-Tank-Top-WHITE-0095067807.jpg"
        ]
      }
    ]
  },
  {
    "id": "P000214807",
    "name": "Sag Harbor Slimming Cargo Skimmer Shorts",
    "long_description": "Slenderizing skimmer shorts by Sag Harbor offer a mesh tummy trimming panel, comfort waistband, and side cargo pocket. Easy wear and care with a bit of stretch make these shorts a casual wear favorite.",
    "brand": "Sag Harbor",
    "slug": "/sag-harbor-slimming-cargo-skimmer-shorts-p000214807/p",
    "product_ref": "P000214807",
    "product_type": null,
    "seo_title": "Sag Harbor Slimming Cargo Skimmer Shorts",
    "seo_description": "Slenderizing skimmer shorts by Sag Harbor offer a mesh tummy trimming panel, comfort waistband, and side cargo pocket. Easy wear and care with a bit of stretch make these shorts a casual wear favorite.",
    "seo_keywords": "Sag Harbor Slimming Cargo Skimmer Shorts, Sag Harbor",
    "display_on_site": true,
    "tax_code": "txcd_99999999",
    "related_products": [],
    "reviews": {
      "bayesian_avg": 4.5,
      "count": 175,
      "rating": 5
    },
    "hierarchical_categories": {
      "lvl0": "Women",
      "lvl1": "Women > Misses Apparel",
      "lvl2": "Women > Misses Apparel > Shorts"
    },
    "list_categories": [
      "Women",
      "Misses Apparel",
      "Shorts"
    ],
    "created_at": null,
    "updated_at": null,
    "created_by": null,
    "updated_by": null,
    "defining_attributes": {
      "color": "Color",
      "size": "Size"
    },
    "descriptive_attributes": {
      "Country of Origin": "United States",
      "Material": "Cotton",
      "Care Instructions": "Machine Wash"
    },
    "default_variant": "0095701670",
    "variants": [
      {
        "defining_attributes": {
          "color": "WHITE",
          "size": "8"
        },
        "abbreviated_color": "",
        "sku": "0095701670",
        "height": 0,
        "width": 0,
        "length": 0,
        "weight": 0,
        "weight_unit": "lb",
        "packaging": {
          "height": 0,
          "width": 0,
          "length": 0,
          "weight": 0,
          "weight_unit": "lb"
        },
        "image_urls": [
          "https://res.cloudinary.com/dau8m6xke/image/upload/products/Sag-Harbor-Slimming-Cargo-Skimmer-Shorts-WHITE-0095701670.jpg"
        ]
      },
      {
        "defining_attributes": {
          "color": "WHITE",
          "size": "10"
        },
        "abbreviated_color": "",
        "sku": "0095701682",
        "height": 0,
        "width": 0,
        "length": 0,
        "weight": 0,
        "weight_unit": "lb",
        "packaging": {
          "height": 0,
          "width": 0,
          "length": 0,
          "weight": 0,
          "weight_unit": "lb"
        },
        "image_urls": [
          "https://res.cloudinary.com/dau8m6xke/image/upload/products/Sag-Harbor-Slimming-Cargo-Skimmer-Shorts-WHITE-0095701682.jpg"
        ]
      },
      {
        "defining_attributes": {
          "color": "WHITE",
          "size": "12"
        },
        "abbreviated_color": "",
        "sku": "0095701694",
        "height": 0,
        "width": 0,
        "length": 0,
        "weight": 0,
        "weight_unit": "lb",
        "packaging": {
          "height": 0,
          "width": 0,
          "length": 0,
          "weight": 0,
          "weight_unit": "lb"
        },
        "image_urls": [
          "https://res.cloudinary.com/dau8m6xke/image/upload/products/Sag-Harbor-Slimming-Cargo-Skimmer-Shorts-WHITE-0095701694.jpg"
        ]
      },
      {
        "defining_attributes": {
          "size": "14",
          "color": "WHITE"
        },
        "abbreviated_color": "",
        "sku": "0095701709",
        "height": 0,
        "width": 0,
        "length": 0,
        "weight": 0,
        "weight_unit": "lb",
        "packaging": {
          "height": 0,
          "width": 0,
          "length": 0,
          "weight": 0,
          "weight_unit": "lb"
        },
        "image_urls": [
          "https://res.cloudinary.com/dau8m6xke/image/upload/products/Sag-Harbor-Slimming-Cargo-Skimmer-Shorts-WHITE-0095701709.jpg"
        ]
      },
      {
        "defining_attributes": {
          "size": "16",
          "color": "WHITE"
        },
        "abbreviated_color": "",
        "sku": "0095701712",
        "height": 0,
        "width": 0,
        "length": 0,
        "weight": 0,
        "weight_unit": "lb",
        "packaging": {
          "height": 0,
          "width": 0,
          "length": 0,
          "weight": 0,
          "weight_unit": "lb"
        },
        "image_urls": [
          "https://res.cloudinary.com/dau8m6xke/image/upload/products/Sag-Harbor-Slimming-Cargo-Skimmer-Shorts-WHITE-0095701712.jpg"
        ]
      },
      {
        "defining_attributes": {
          "size": "18",
          "color": "WHITE"
        },
        "abbreviated_color": "",
        "sku": "0095701724",
        "height": 0,
        "width": 0,
        "length": 0,
        "weight": 0,
        "weight_unit": "lb",
        "packaging": {
          "height": 0,
          "width": 0,
          "length": 0,
          "weight": 0,
          "weight_unit": "lb"
        },
        "image_urls": [
          "https://res.cloudinary.com/dau8m6xke/image/upload/products/Sag-Harbor-Slimming-Cargo-Skimmer-Shorts-WHITE-0095701724.jpg"
        ]
      },
      {
        "defining_attributes": {
          "size": "8",
          "color": "BLACK"
        },
        "abbreviated_color": "",
        "sku": "0095701763",
        "height": 0,
        "width": 0,
        "length": 0,
        "weight": 0,
        "weight_unit": "lb",
        "packaging": {
          "height": 0,
          "width": 0,
          "length": 0,
          "weight": 0,
          "weight_unit": "lb"
        },
        "image_urls": [
          "https://res.cloudinary.com/dau8m6xke/image/upload/products/Sag-Harbor-Slimming-Cargo-Skimmer-Shorts-BLACK-0095701763.jpg"
        ]
      },
      {
        "defining_attributes": {
          "size": "10",
          "color": "BLACK"
        },
        "abbreviated_color": "",
        "sku": "0095701776",
        "height": 0,
        "width": 0,
        "length": 0,
        "weight": 0,
        "weight_unit": "lb",
        "packaging": {
          "height": 0,
          "width": 0,
          "length": 0,
          "weight": 0,
          "weight_unit": "lb"
        },
        "image_urls": [
          "https://res.cloudinary.com/dau8m6xke/image/upload/products/Sag-Harbor-Slimming-Cargo-Skimmer-Shorts-BLACK-0095701776.jpg"
        ]
      },
      {
        "defining_attributes": {
          "color": "BLACK",
          "size": "14"
        },
        "abbreviated_color": "",
        "sku": "0095701790",
        "height": 0,
        "width": 0,
        "length": 0,
        "weight": 0,
        "weight_unit": "lb",
        "packaging": {
          "height": 0,
          "width": 0,
          "length": 0,
          "weight": 0,
          "weight_unit": "lb"
        },
        "image_urls": [
          "https://res.cloudinary.com/dau8m6xke/image/upload/products/Sag-Harbor-Slimming-Cargo-Skimmer-Shorts-BLACK-0095701790.jpg"
        ]
      },
      {
        "defining_attributes": {
          "size": "16",
          "color": "BLACK"
        },
        "abbreviated_color": "",
        "sku": "0095701806",
        "height": 0,
        "width": 0,
        "length": 0,
        "weight": 0,
        "weight_unit": "lb",
        "packaging": {
          "height": 0,
          "width": 0,
          "length": 0,
          "weight": 0,
          "weight_unit": "lb"
        },
        "image_urls": [
          "https://res.cloudinary.com/dau8m6xke/image/upload/products/Sag-Harbor-Slimming-Cargo-Skimmer-Shorts-BLACK-0095701806.jpg"
        ]
      },
      {
        "defining_attributes": {
          "color": "YELLOW",
          "size": "8"
        },
        "abbreviated_color": "",
        "sku": "0095701860",
        "height": 0,
        "width": 0,
        "length": 0,
        "weight": 0,
        "weight_unit": "lb",
        "packaging": {
          "height": 0,
          "width": 0,
          "length": 0,
          "weight": 0,
          "weight_unit": "lb"
        },
        "image_urls": [
          "https://res.cloudinary.com/dau8m6xke/image/upload/products/Sag-Harbor-Slimming-Cargo-Skimmer-Shorts-YELLOW-0095701860.jpg"
        ]
      },
      {
        "defining_attributes": {
          "color": "YELLOW",
          "size": "10"
        },
        "abbreviated_color": "",
        "sku": "0095701873",
        "height": 0,
        "width": 0,
        "length": 0,
        "weight": 0,
        "weight_unit": "lb",
        "packaging": {
          "height": 0,
          "width": 0,
          "length": 0,
          "weight": 0,
          "weight_unit": "lb"
        },
        "image_urls": [
          "https://res.cloudinary.com/dau8m6xke/image/upload/products/Sag-Harbor-Slimming-Cargo-Skimmer-Shorts-YELLOW-0095701873.jpg"
        ]
      },
      {
        "defining_attributes": {
          "size": "12",
          "color": "YELLOW"
        },
        "abbreviated_color": "",
        "sku": "0095701885",
        "height": 0,
        "width": 0,
        "length": 0,
        "weight": 0,
        "weight_unit": "lb",
        "packaging": {
          "height": 0,
          "width": 0,
          "length": 0,
          "weight": 0,
          "weight_unit": "lb"
        },
        "image_urls": [
          "https://res.cloudinary.com/dau8m6xke/image/upload/products/Sag-Harbor-Slimming-Cargo-Skimmer-Shorts-YELLOW-0095701885.jpg"
        ]
      },
      {
        "defining_attributes": {
          "color": "YELLOW",
          "size": "14"
        },
        "abbreviated_color": "",
        "sku": "0095701897",
        "height": 0,
        "width": 0,
        "length": 0,
        "weight": 0,
        "weight_unit": "lb",
        "packaging": {
          "height": 0,
          "width": 0,
          "length": 0,
          "weight": 0,
          "weight_unit": "lb"
        },
        "image_urls": [
          "https://res.cloudinary.com/dau8m6xke/image/upload/products/Sag-Harbor-Slimming-Cargo-Skimmer-Shorts-YELLOW-0095701897.jpg"
        ]
      },
      {
        "defining_attributes": {
          "color": "YELLOW",
          "size": "16"
        },
        "abbreviated_color": "",
        "sku": "0095701903",
        "height": 0,
        "width": 0,
        "length": 0,
        "weight": 0,
        "weight_unit": "lb",
        "packaging": {
          "height": 0,
          "width": 0,
          "length": 0,
          "weight": 0,
          "weight_unit": "lb"
        },
        "image_urls": [
          "https://res.cloudinary.com/dau8m6xke/image/upload/products/Sag-Harbor-Slimming-Cargo-Skimmer-Shorts-YELLOW-0095701903.jpg"
        ]
      },
      {
        "defining_attributes": {
          "color": "YELLOW",
          "size": "18"
        },
        "abbreviated_color": "",
        "sku": "0095701916",
        "height": 0,
        "width": 0,
        "length": 0,
        "weight": 0,
        "weight_unit": "lb",
        "packaging": {
          "height": 0,
          "width": 0,
          "length": 0,
          "weight": 0,
          "weight_unit": "lb"
        },
        "image_urls": [
          "https://res.cloudinary.com/dau8m6xke/image/upload/products/Sag-Harbor-Slimming-Cargo-Skimmer-Shorts-YELLOW-0095701916.jpg"
        ]
      },
      {
        "defining_attributes": {
          "color": "COSMIC BLUE",
          "size": "8"
        },
        "abbreviated_color": "",
        "sku": "0095702026",
        "height": 0,
        "width": 0,
        "length": 0,
        "weight": 0,
        "weight_unit": "lb",
        "packaging": {
          "height": 0,
          "width": 0,
          "length": 0,
          "weight": 0,
          "weight_unit": "lb"
        },
        "image_urls": [
          "https://res.cloudinary.com/dau8m6xke/image/upload/products/Sag-Harbor-Slimming-Cargo-Skimmer-Shorts-COSMIC-BLUE-0095702026.jpg"
        ]
      },
      {
        "defining_attributes": {
          "color": "COSMIC BLUE",
          "size": "10"
        },
        "abbreviated_color": "",
        "sku": "0095702038",
        "height": 0,
        "width": 0,
        "length": 0,
        "weight": 0,
        "weight_unit": "lb",
        "packaging": {
          "height": 0,
          "width": 0,
          "length": 0,
          "weight": 0,
          "weight_unit": "lb"
        },
        "image_urls": [
          "https://res.cloudinary.com/dau8m6xke/image/upload/products/Sag-Harbor-Slimming-Cargo-Skimmer-Shorts-COSMIC-BLUE-0095702038.jpg"
        ]
      },
      {
        "defining_attributes": {
          "color": "COSMIC BLUE",
          "size": "12"
        },
        "abbreviated_color": "",
        "sku": "0095702041",
        "height": 0,
        "width": 0,
        "length": 0,
        "weight": 0,
        "weight_unit": "lb",
        "packaging": {
          "height": 0,
          "width": 0,
          "length": 0,
          "weight": 0,
          "weight_unit": "lb"
        },
        "image_urls": [
          "https://res.cloudinary.com/dau8m6xke/image/upload/products/Sag-Harbor-Slimming-Cargo-Skimmer-Shorts-COSMIC-BLUE-0095702041.jpg"
        ]
      },
      {
        "defining_attributes": {
          "color": "COSMIC BLUE",
          "size": "14"
        },
        "abbreviated_color": "",
        "sku": "0095702053",
        "height": 0,
        "width": 0,
        "length": 0,
        "weight": 0,
        "weight_unit": "lb",
        "packaging": {
          "height": 0,
          "width": 0,
          "length": 0,
          "weight": 0,
          "weight_unit": "lb"
        },
        "image_urls": [
          "https://res.cloudinary.com/dau8m6xke/image/upload/products/Sag-Harbor-Slimming-Cargo-Skimmer-Shorts-COSMIC-BLUE-0095702053.jpg"
        ]
      },
      {
        "defining_attributes": {
          "size": "16",
          "color": "COSMIC BLUE"
        },
        "abbreviated_color": "",
        "sku": "0095702065",
        "height": 0,
        "width": 0,
        "length": 0,
        "weight": 0,
        "weight_unit": "lb",
        "packaging": {
          "height": 0,
          "width": 0,
          "length": 0,
          "weight": 0,
          "weight_unit": "lb"
        },
        "image_urls": [
          "https://res.cloudinary.com/dau8m6xke/image/upload/products/Sag-Harbor-Slimming-Cargo-Skimmer-Shorts-COSMIC-BLUE-0095702065.jpg"
        ]
      },
      {
        "defining_attributes": {
          "color": "COSMIC BLUE",
          "size": "18"
        },
        "abbreviated_color": "",
        "sku": "0095702078",
        "height": 0,
        "width": 0,
        "length": 0,
        "weight": 0,
        "weight_unit": "lb",
        "packaging": {
          "height": 0,
          "width": 0,
          "length": 0,
          "weight": 0,
          "weight_unit": "lb"
        },
        "image_urls": [
          "https://res.cloudinary.com/dau8m6xke/image/upload/products/Sag-Harbor-Slimming-Cargo-Skimmer-Shorts-COSMIC-BLUE-0095702078.jpg"
        ]
      }
    ]
  }]